{"version":"1.2.5","title":"Duskfire Asylum","story":"The asylum is situated deep in the desert, protected by the dangerous local fauna and harsh weather. Recently a fearsome blood-sucking wolf has made its lair here. Word is that Patrinn, a legendary tablet, is hidden here.","rects":[{"x":1,"y":-1,"w":5,"h":3},{"x":0,"y":-9,"w":7,"h":7},{"x":0,"y":3,"w":7,"h":7},{"x":8,"y":-8,"w":6,"h":3,"ending":true},{"x":-7,"y":-8,"w":6,"h":3},{"x":8,"y":6,"w":6,"h":3},{"x":-7,"y":6,"w":6,"h":3},{"x":0,"y":0,"w":1,"h":1},{"x":3,"y":-2,"w":1,"h":1},{"x":3,"y":2,"w":1,"h":1},{"x":7,"y":-7,"w":1,"h":1},{"x":-1,"y":-7,"w":1,"h":1},{"x":7,"y":7,"w":1,"h":1},{"x":-1,"y":7,"w":1,"h":1}],"doors":[{"x":0,"y":0,"dir":{"x":1,"y":0},"type":3},{"x":3,"y":-2,"dir":{"x":0,"y":-1},"type":5},{"x":3,"y":2,"dir":{"x":0,"y":1},"type":1},{"x":7,"y":-7,"dir":{"x":1,"y":0},"type":1},{"x":-1,"y":-7,"dir":{"x":-1,"y":0},"type":1},{"x":7,"y":7,"dir":{"x":1,"y":0},"type":1},{"x":-1,"y":7,"dir":{"x":-1,"y":0},"type":1}],"notes":[{"text":"A round iron double door to the north.","ref":"1","pos":{"x":3.5,"y":0.5}},{"text":"A reinforced chest with a silver necklace in it.","ref":"2","pos":{"x":3.5,"y":6.5}},{"text":"A dying halfling, some gold among his belongings.","ref":"3","pos":{"x":-4,"y":-6.5}}],"columns":[{"x":2,"y":0},{"x":2,"y":1},{"x":3,"y":0},{"x":3,"y":1},{"x":4,"y":0},{"x":4,"y":1},{"x":5,"y":0},{"x":5,"y":1}],"water":[]}